udata_geoplatform/__init__.py
udata_geoplatform/preview.py
udata_geoplatform/settings.py
udata_geoplatform-2.0.0.dist-info/METADATA
udata_geoplatform-2.0.0.dist-info/WHEEL
udata_geoplatform-2.0.0.dist-info/entry_points.txt
udata_geoplatform-2.0.0.dist-info/top_level.txt
udata_geoplatform-2.0.0.dist-info/RECORD
