Metadata-Version: 2.1
Name: udata-geoplatform
Version: 2.0.0
Summary: Connects uData with Geoplatform (geo.data.gouv.fr)
Home-page: https://github.com/opendatateam/udata-geoplatform
Author: Open Data Team
Author-email: contact@opendata.team
License: AGPL
Keywords: udata,harvester,uData Geoplatform connector
Platform: UNKNOWN
Classifier: Development Status :: 3 - Alpha
Classifier: Programming Language :: Python
Classifier: Environment :: Web Environment
Classifier: Operating System :: OS Independent
Classifier: Intended Audience :: Developers
Classifier: Topic :: System :: Software Distribution
Classifier: Programming Language :: Python
Classifier: Programming Language :: Python :: 3
Classifier: Programming Language :: Python :: 3.7
Classifier: Topic :: Software Development :: Libraries :: Python Modules
Requires-Python: >=3.7
Requires-Dist: udata (>=2.0.0)
Provides-Extra: test
Requires-Dist: httpretty (==0.9.7) ; extra == 'test'
Requires-Dist: mock (==3.0.5) ; extra == 'test'
Requires-Dist: pytest-flask (==0.15.0) ; extra == 'test'
Requires-Dist: pytest-sugar (==0.9.2) ; extra == 'test'
Requires-Dist: pytest (==4.6.3) ; extra == 'test'
